{"GlobalPropertiesHash":"rWtDGPUoCtCkZWs8MqC2KDWWDAJztyjJLtOxCAfRJPo=","FingerprintPatternsHash":"gq3WsqcKBUGTSNle7RKKyXRIwh7M8ccEqOqYvIzoM04=","PropertyOverridesHash":"8ZRc1sGeVrPBx4lD717BgRaQekyh78QKV9SKsdt638U=","InputHashes":["5HHnk5c8wwM471JRHUXHjauLok3PRMBPH5wjQbbbc94=","xK\u002BUzDLQ/Vod6Sd\u002BKkWpjipbEbt4qxF9AAdJmLDEfxU=","F9bA\u002BPljymlmKvHCEb4nXIdOv\u002BQBQ4jrU4455pc5mhs=","pNCQmgB1kSY6FH4jZ9xmhWxw88SrJnnROK2e8Ney1ks=","zpYxx987mHaNDz/KWF8yUm9GjVkYUTog423EepqHias="],"CachedAssets":{"xK\u002BUzDLQ/Vod6Sd\u002BKkWpjipbEbt4qxF9AAdJmLDEfxU=":{"Identity":"C:\\Users\\Carlos\\Desktop\\Estudo\\CSharp\\GitC#\\CSharp\\DownTube\\wwwroot\\script.js","SourceId":"DownTube","SourceType":"Discovered","ContentRoot":"C:\\Users\\Carlos\\Desktop\\Estudo\\CSharp\\GitC#\\CSharp\\DownTube\\wwwroot\\","BasePath":"_content/DownTube","RelativePath":"script#[.{fingerprint}]?.js","AssetKind":"All","AssetMode":"All","AssetRole":"Primary","AssetMergeBehavior":null,"AssetMergeSource":"","RelatedAsset":null,"AssetTraitName":null,"AssetTraitValue":null,"Fingerprint":"hfxf26ohwk","Integrity":"/TA6FEycQR9R58DLH65YW9n9r9jSrxVLMqkYTgE9\u002BYA=","CopyToOutputDirectory":"Never","CopyToPublishDirectory":"PreserveNewest","OriginalItemSpec":"wwwroot\\script.js","FileLength":1109,"LastWriteTime":"2025-08-26T01:06:05.0169386+00:00"},"5HHnk5c8wwM471JRHUXHjauLok3PRMBPH5wjQbbbc94=":{"Identity":"C:\\Users\\Carlos\\Desktop\\Estudo\\CSharp\\GitC#\\CSharp\\DownTube\\wwwroot\\index.html","SourceId":"DownTube","SourceType":"Discovered","ContentRoot":"C:\\Users\\Carlos\\Desktop\\Estudo\\CSharp\\GitC#\\CSharp\\DownTube\\wwwroot\\","BasePath":"_content/DownTube","RelativePath":"index#[.{fingerprint}]?.html","AssetKind":"All","AssetMode":"All","AssetRole":"Primary","AssetMergeBehavior":null,"AssetMergeSource":"","RelatedAsset":null,"AssetTraitName":null,"AssetTraitValue":null,"Fingerprint":"q1xdhur6dq","Integrity":"jgFOfhuFyBwONJpPIhn7f1kBgleyibDeAxtXgGvCC9Y=","CopyToOutputDirectory":"Never","CopyToPublishDirectory":"PreserveNewest","OriginalItemSpec":"wwwroot\\index.html","FileLength":668,"LastWriteTime":"2025-08-26T01:05:19.6772579+00:00"},"F9bA\u002BPljymlmKvHCEb4nXIdOv\u002BQBQ4jrU4455pc5mhs=":{"Identity":"C:\\Users\\Carlos\\Desktop\\Estudo\\CSharp\\GitC#\\CSharp\\DownTube\\wwwroot\\style.css","SourceId":"DownTube","SourceType":"Discovered","ContentRoot":"C:\\Users\\Carlos\\Desktop\\Estudo\\CSharp\\GitC#\\CSharp\\DownTube\\wwwroot\\","BasePath":"_content/DownTube","RelativePath":"style#[.{fingerprint}]?.css","AssetKind":"All","AssetMode":"All","AssetRole":"Primary","AssetMergeBehavior":null,"AssetMergeSource":"","RelatedAsset":null,"AssetTraitName":null,"AssetTraitValue":null,"Fingerprint":"ekpafzuax8","Integrity":"7tpvYgjPciYyHqT/Yeybk/3gMtXdJc/0mklB\u002B8prKBY=","CopyToOutputDirectory":"Never","CopyToPublishDirectory":"PreserveNewest","OriginalItemSpec":"wwwroot\\style.css","FileLength":17,"LastWriteTime":"2025-08-25T21:36:33.5354405+00:00"}},"CachedCopyCandidates":{}}